ChangeLog
INSTALL.rst
MANIFEST.in
README.rst
setup.py
bin/ly
bin/ly-server
doc/Makefile
doc/command.rst
doc/conf.py
doc/index.rst
doc/ly.cli.rst
doc/ly.data.rst
doc/ly.lex.rst
doc/ly.music.rst
doc/ly.musicxml.rst
doc/ly.pitch.rst
doc/ly.rst
doc/ly.server.rst
doc/ly.xml.rst
doc/servercmd.rst
ly/__init__.py
ly/__main__.py
ly/barcheck.py
ly/colorize.py
ly/cursortools.py
ly/docinfo.py
ly/document.py
ly/dom.py
ly/duration.py
ly/etreeutil.py
ly/indent.py
ly/node.py
ly/pkginfo.py
ly/reformat.py
ly/rests.py
ly/rhythm.py
ly/slexer.py
ly/util.py
ly/words.py
ly/cli/__init__.py
ly/cli/command.py
ly/cli/doc.py
ly/cli/main.py
ly/cli/setvar.py
ly/data/__init__.py
ly/data/_data.py
ly/data/_lilypond_data.py
ly/data/_scheme_data.py
ly/data/makeschemedata.py
ly/lex/__init__.py
ly/lex/_mode.py
ly/lex/_token.py
ly/lex/docbook.py
ly/lex/html.py
ly/lex/latex.py
ly/lex/lilypond.py
ly/lex/mup.py
ly/lex/scheme.py
ly/lex/texinfo.py
ly/music/__init__.py
ly/music/event.py
ly/music/items.py
ly/music/read.py
ly/musicxml/__init__.py
ly/musicxml/create_musicxml.py
ly/musicxml/ly2xml_mediator.py
ly/musicxml/lymus2musxml.py
ly/musicxml/midi_sound_map.py
ly/musicxml/xml_objs.py
ly/pitch/__init__.py
ly/pitch/abs2rel.py
ly/pitch/rel2abs.py
ly/pitch/transform.py
ly/pitch/translate.py
ly/pitch/transpose.py
ly/server/__init__.py
ly/server/command.py
ly/server/doc.py
ly/server/handler.py
ly/server/main.py
ly/server/options.py
ly/server/testjson.py
ly/xml/__init__.py
ly/xml/xml-export-init.ly
ly/xml/xml-export.ily
python_ly.egg-info/PKG-INFO
python_ly.egg-info/SOURCES.txt
python_ly.egg-info/dependency_links.txt
python_ly.egg-info/top_level.txt