Metadata-Version: 1.2
Name: python-ly
Version: 0.9.6
Summary: Tool and library for manipulating LilyPond files
Home-page: https://github.com/wbsoft/python-ly
Maintainer: Wilbert Berendsen
Maintainer-email: info@frescobaldi.org
License: GPL
Platform: UNKNOWN
Classifier: Development Status :: 4 - Beta
Classifier: License :: OSI Approved :: GNU General Public License (GPL)
Classifier: Operating System :: MacOS :: MacOS X
Classifier: Operating System :: Microsoft :: Windows
Classifier: Operating System :: POSIX
Classifier: Programming Language :: Python :: 2.7
Classifier: Programming Language :: Python :: 3
Classifier: Topic :: Multimedia :: Sound/Audio
Classifier: Topic :: Text Editors
